<?xml version="1.0"?>
<!DOCTYPE vortaro SYSTEM "../dtd/vokoxml.dtd">

<vortaro>
<art mrk="$Id$">
<kap>
<rad>bolus</rad>/o
</kap>
<drv mrk="bolus.0o">
<kap><tld/>o</kap>
<uzo tip="fak">MED</uzo>
<snc>
<dif>
Granda <ref tip="super" cel="pilol.0o">pilolo</ref>, kiu pezas pli ol 
kvindek centigramojn. 
</dif>
<refgrp tip="vid">
<ref cel="granol.0o">granolo</ref>.
</refgrp>
</snc>
<trd lng="en">bolus</trd>
<trd lng="fr">bol <klr tip="ind">(grosse pilule)</klr></trd>
</drv>
</art>
<!--
$Log$
Revision 1.4  2001/02/17 19:47:56  revo
Marc Bavant: +trd fr, +ref al pilolo

-->
</vortaro>

