<?xml version="1.0"?>
<!DOCTYPE vortaro SYSTEM "../dtd/vokoxml.dtd">

<vortaro>
<art mrk="$Id$">
<kap>
<ofc>*</ofc>
<rad>fremd</rad>/a
</kap>
<drv mrk="fremd.0a">
<kap><ofc>*</ofc><tld/>a</kap>
<snc num="1">
<dif>
Alilanda eksterlanda: <ekz>la <tld/>aj lingvoj, homoj, landoj, kutimoj;
</ekz> <ekz>ministro por <tld/>aj aferoj.
</ekz>
</dif>
<refgrp tip="sin">
<ref cel="ekzot">ekzota</ref>,
<ref cel="mar">transmara</ref>.
</refgrp>
</snc>
<snc num="2">
<dif>
Ekstera k senrilata al la koncernata persono a&ubreve; afero; malpropra, aliula: <ekz>tiuj fratoj fari&gcirc;is tute <tld/>aj unuj al aliaj<fnt>Z</fnt>;
</ekz> <ekz><tld/>a malfeli&ccirc;o ne instruas<fnt>Z</fnt>;
</ekz> <ekz>diskuto tute <tld/>a je la temo;
</ekz> <ekz>li estas <tld/>a al nia societo;
</ekz> <ekz>al homo nenio homa devas esti <tld/>a;
</ekz> <ekz>&gcirc;entileco estas al li <tld/>a;
</ekz> <ekz>ne dolorigas frapo sur <tld/>a kapo<fnt>Z</fnt>
(<ref tip="vid" cel="najbar.0a">najbara</ref>);
</ekz> <ekz>el <tld/>a po&scirc;o oni pagas facile<fnt>Z</fnt>; 
</ekz> <ekz>reciproka <tld/>eco dividas inter si la naturajn 
filojn de sama lando<fnt>Z</fnt>; 
</ekz> <ekz>vivi <tld/>ule en iu lando<fnt>Z</fnt>; 
</ekz> <ekz>pli k pli lar&gcirc;i&gcirc;as la <tld/>i&gcirc;o inter la 
patro k liaj infanoj.  
</ekz>
</dif>
</snc>
<trd lng="en">strange</trd>
</drv>
</art></vortaro>
